{
  "scrapedAt": "2025-12-28T16:50:22.168Z",
  "sourceUrl": "https://webap.nkust.edu.tw/nkust/ag_pro/ag202.jsp",
  "request": {
    "yms_yms": "112#1",
    "cmp_area_id": "2",
    "dgr_id": "14",
    "unt_id": "UH53",
    "clyear": "%",
    "week": "%",
    "period": "%",
    "reading": "reading"
  },
  "unit": {
    "id": "UH53",
    "label": "(管理學院)人力資源發展系"
  },
  "warning": null,
  "header": [
    "選課代號",
    "上課校區",
    "部別",
    "科系",
    "班級",
    "合班班級",
    "永久課號",
    "科目名稱",
    "學分",
    "授課時數",
    "實習時數",
    "必/選",
    "授課教師",
    "教室",
    "修課人數",
    "人數上限",
    "上課時間",
    "全英語授課",
    "遠距教學",
    "授課大綱",
    "備註"
  ],
  "courses": [
    {
      "selectCode": "1618",
      "campus": "燕巢校區",
      "division": "日間部四技",
      "department": "人力資源發展系",
      "className": "四人一甲",
      "combinedClassName": "",
      "courseCode": "251C10122",
      "courseName": "民法",
      "credits": 2,
      "lectureHours": 2,
      "labHours": 0,
      "requiredOrElective": "選修",
      "instructor": "鄭克強",
      "classroom": "HS528",
      "enrolled": 62,
      "capacity": 72,
      "time": "(二)5-6",
      "englishTaught": "否",
      "distanceLearning": "否",
      "syllabus": null,
      "note": ""
    },
    {
      "selectCode": "1619",
      "campus": "燕巢校區",
      "division": "日間部四技",
      "department": "人力資源發展系",
      "className": "四人一甲",
      "combinedClassName": "",
      "courseCode": "251C10297",
      "courseName": "企業概論",
      "credits": 3,
      "lectureHours": 3,
      "labHours": 0,
      "requiredOrElective": "選修",
      "instructor": "黃建榮",
      "classroom": "HS528",
      "enrolled": 74,
      "capacity": 72,
      "time": "(五)2-4",
      "englishTaught": "否",
      "distanceLearning": "否",
      "syllabus": null,
      "note": ""
    },
    {
      "selectCode": "1620",
      "campus": "燕巢校區",
      "division": "日間部四技",
      "department": "人力資源發展系",
      "className": "四人一甲",
      "combinedClassName": "",
      "courseCode": "251C10158",
      "courseName": "考銓制度",
      "credits": 2,
      "lectureHours": 2,
      "labHours": 0,
      "requiredOrElective": "選修",
      "instructor": "鄭克強",
      "classroom": "HS528",
      "enrolled": 59,
      "capacity": 72,
      "time": "(二)7-8",
      "englishTaught": "否",
      "distanceLearning": "否",
      "syllabus": null,
      "note": ""
    },
    {
      "selectCode": "1621",
      "campus": "燕巢校區",
      "division": "日間部四技",
      "department": "人力資源發展系",
      "className": "四人一甲",
      "combinedClassName": "",
      "courseCode": "251C10294",
      "courseName": "社會學(一)",
      "credits": 2,
      "lectureHours": 2,
      "labHours": 0,
      "requiredOrElective": "選修",
      "instructor": "王湧泉",
      "classroom": "HS528",
      "enrolled": 66,
      "capacity": 72,
      "time": "(一)5-6",
      "englishTaught": "否",
      "distanceLearning": "否",
      "syllabus": null,
      "note": ""
    },
    {
      "selectCode": "1622",
      "campus": "燕巢校區",
      "division": "日間部四技",
      "department": "人力資源發展系",
      "className": "四人一甲",
      "combinedClassName": "",
      "courseCode": "251C00086",
      "courseName": "統計學(一)",
      "credits": 3,
      "lectureHours": 3,
      "labHours": 0,
      "requiredOrElective": "必修",
      "instructor": "許淑寬",
      "classroom": "HS528",
      "enrolled": 68,
      "capacity": 72,
      "time": "(一)2-4",
      "englishTaught": "否",
      "distanceLearning": "否",
      "syllabus": null,
      "note": ""
    },
    {
      "selectCode": "1623",
      "campus": "燕巢校區",
      "division": "日間部四技",
      "department": "人力資源發展系",
      "className": "四人一甲",
      "combinedClassName": "",
      "courseCode": "251C00099",
      "courseName": "經濟學(一)",
      "credits": 3,
      "lectureHours": 3,
      "labHours": 0,
      "requiredOrElective": "必修",
      "instructor": "翁慈君",
      "classroom": "HS528",
      "enrolled": 63,
      "capacity": 72,
      "time": "(四)2-4",
      "englishTaught": "否",
      "distanceLearning": "否",
      "syllabus": null,
      "note": ""
    },
    {
      "selectCode": "1624",
      "campus": "燕巢校區",
      "division": "日間部四技",
      "department": "人力資源發展系",
      "className": "四人一甲",
      "combinedClassName": "",
      "courseCode": "251C00088",
      "courseName": "管理學",
      "credits": 3,
      "lectureHours": 3,
      "labHours": 0,
      "requiredOrElective": "必修",
      "instructor": "黃瓊慧",
      "classroom": "HS528",
      "enrolled": 57,
      "capacity": 72,
      "time": "(二)2-4",
      "englishTaught": "否",
      "distanceLearning": "否",
      "syllabus": null,
      "note": ""
    },
    {
      "selectCode": "1625",
      "campus": "燕巢校區",
      "division": "日間部四技",
      "department": "人力資源發展系",
      "className": "四人一甲",
      "combinedClassName": "",
      "courseCode": "251C10237",
      "courseName": "商業文書處理軟體",
      "credits": 3,
      "lectureHours": 3,
      "labHours": 0,
      "requiredOrElective": "選修",
      "instructor": "施富川",
      "classroom": "HS519",
      "enrolled": 40,
      "capacity": 70,
      "time": "(四)5-7",
      "englishTaught": "否",
      "distanceLearning": "否",
      "syllabus": null,
      "note": ""
    },
    {
      "selectCode": "4149",
      "campus": "燕巢校區",
      "division": "日間部四技",
      "department": "人力資源發展系",
      "className": "四人一甲",
      "combinedClassName": "",
      "courseCode": "800C00014",
      "courseName": "企業倫理與永續發展",
      "credits": 2,
      "lectureHours": 2,
      "labHours": 0,
      "requiredOrElective": "必修",
      "instructor": "林思吟",
      "classroom": "MB523",
      "enrolled": 64,
      "capacity": 60,
      "time": "(二)5-6",
      "englishTaught": "否",
      "distanceLearning": "否",
      "syllabus": null,
      "note": ""
    },
    {
      "selectCode": "4150",
      "campus": "燕巢校區",
      "division": "日間部四技",
      "department": "人力資源發展系",
      "className": "四人一甲",
      "combinedClassName": "",
      "courseCode": "800C00014",
      "courseName": "企業倫理與永續發展",
      "credits": 2,
      "lectureHours": 2,
      "labHours": 0,
      "requiredOrElective": "必修",
      "instructor": "王綺楓",
      "classroom": "MB324",
      "enrolled": 51,
      "capacity": 61,
      "time": "(一)5-6",
      "englishTaught": "否",
      "distanceLearning": "否",
      "syllabus": null,
      "note": ""
    },
    {
      "selectCode": "4234",
      "campus": "燕巢校區",
      "division": "日間部四技",
      "department": "人力資源發展系",
      "className": "四人一甲",
      "combinedClassName": "",
      "courseCode": "041C00176",
      "courseName": "中文閱讀與表達(一)",
      "credits": 2,
      "lectureHours": 2,
      "labHours": 0,
      "requiredOrElective": "必修",
      "instructor": "蔡文彥",
      "classroom": "HS528",
      "enrolled": 56,
      "capacity": 55,
      "time": "(三)3-4",
      "englishTaught": "否",
      "distanceLearning": "否",
      "syllabus": null,
      "note": "班級: 四人一甲"
    },
    {
      "selectCode": "5249",
      "campus": "燕巢校區",
      "division": "日間部四技",
      "department": "人力資源發展系",
      "className": "四人一甲",
      "combinedClassName": "",
      "courseCode": "080C00001",
      "courseName": "服務教育(一)",
      "credits": 0,
      "lectureHours": 2,
      "labHours": 0,
      "requiredOrElective": "必修",
      "instructor": "許淑寬",
      "classroom": "教室未定",
      "enrolled": 57,
      "capacity": 70,
      "time": "(一)A(三)A",
      "englishTaught": "否",
      "distanceLearning": "否",
      "syllabus": null,
      "note": "環境服務教育"
    },
    {
      "selectCode": "5359",
      "campus": "燕巢校區",
      "division": "日間部四技",
      "department": "人力資源發展系",
      "className": "四人一甲",
      "combinedClassName": "",
      "courseCode": "050C00037",
      "courseName": "體育(一)",
      "credits": 0,
      "lectureHours": 2,
      "labHours": 0,
      "requiredOrElective": "必修",
      "instructor": "林裕恩",
      "classroom": "",
      "enrolled": 56,
      "capacity": 25,
      "time": "(三)7-8",
      "englishTaught": "否",
      "distanceLearning": "否",
      "syllabus": null,
      "note": "四人資一甲"
    },
    {
      "selectCode": "1626",
      "campus": "燕巢校區",
      "division": "日間部四技",
      "department": "人力資源發展系",
      "className": "四人二甲",
      "combinedClassName": "",
      "courseCode": "251C10119",
      "courseName": "行政學",
      "credits": 2,
      "lectureHours": 2,
      "labHours": 0,
      "requiredOrElective": "選修",
      "instructor": "吳思達",
      "classroom": "HS529",
      "enrolled": 70,
      "capacity": 72,
      "time": "(三)7-8",
      "englishTaught": "否",
      "distanceLearning": "否",
      "syllabus": null,
      "note": ""
    },
    {
      "selectCode": "1627",
      "campus": "燕巢校區",
      "division": "日間部四技",
      "department": "人力資源發展系",
      "className": "四人二甲",
      "combinedClassName": "",
      "courseCode": "251C00102",
      "courseName": "組織行為",
      "credits": 3,
      "lectureHours": 3,
      "labHours": 0,
      "requiredOrElective": "必修",
      "instructor": "董玉娟",
      "classroom": "HS529",
      "enrolled": 73,
      "capacity": 72,
      "time": "(一)2-4",
      "englishTaught": "否",
      "distanceLearning": "否",
      "syllabus": null,
      "note": ""
    },
    {
      "selectCode": "1628",
      "campus": "燕巢校區",
      "division": "日間部四技",
      "department": "人力資源發展系",
      "className": "四人二甲",
      "combinedClassName": "",
      "courseCode": "251C00089",
      "courseName": "勞資關係",
      "credits": 3,
      "lectureHours": 3,
      "labHours": 0,
      "requiredOrElective": "必修",
      "instructor": "王湧泉",
      "classroom": "HS529",
      "enrolled": 69,
      "capacity": 72,
      "time": "(二)5-7",
      "englishTaught": "否",
      "distanceLearning": "否",
      "syllabus": null,
      "note": ""
    },
    {
      "selectCode": "1629",
      "campus": "燕巢校區",
      "division": "日間部四技",
      "department": "人力資源發展系",
      "className": "四人二甲",
      "combinedClassName": "",
      "courseCode": "251C00105",
      "courseName": "人力規劃與任用",
      "credits": 3,
      "lectureHours": 3,
      "labHours": 0,
      "requiredOrElective": "必修",
      "instructor": "陳儀蓉",
      "classroom": "HS519",
      "enrolled": 69,
      "capacity": 70,
      "time": "(五)2-4",
      "englishTaught": "否",
      "distanceLearning": "否",
      "syllabus": null,
      "note": ""
    },
    {
      "selectCode": "1630",
      "campus": "燕巢校區",
      "division": "日間部四技",
      "department": "人力資源發展系",
      "className": "四人二甲",
      "combinedClassName": "",
      "courseCode": "251C10266",
      "courseName": "服務業人力資源管理",
      "credits": 3,
      "lectureHours": 3,
      "labHours": 0,
      "requiredOrElective": "選修",
      "instructor": "陳培銘",
      "classroom": "HS529",
      "enrolled": 67,
      "capacity": 72,
      "time": "(五)5-7",
      "englishTaught": "否",
      "distanceLearning": "否",
      "syllabus": null,
      "note": ""
    },
    {
      "selectCode": "1631",
      "campus": "燕巢校區",
      "division": "日間部四技",
      "department": "人力資源發展系",
      "className": "四人二甲",
      "combinedClassName": "",
      "courseCode": "251C10293",
      "courseName": "組織管理",
      "credits": 3,
      "lectureHours": 3,
      "labHours": 0,
      "requiredOrElective": "選修",
      "instructor": "許淑寬",
      "classroom": "HS529",
      "enrolled": 51,
      "capacity": 72,
      "time": "(二)2-4",
      "englishTaught": "否",
      "distanceLearning": "否",
      "syllabus": null,
      "note": ""
    },
    {
      "selectCode": "1632",
      "campus": "燕巢校區",
      "division": "日間部四技",
      "department": "人力資源發展系",
      "className": "四人二甲",
      "combinedClassName": "",
      "courseCode": "251C10261",
      "courseName": "產業分析",
      "credits": 3,
      "lectureHours": 3,
      "labHours": 0,
      "requiredOrElective": "選修",
      "instructor": "黃瓊慧",
      "classroom": "HS529",
      "enrolled": 72,
      "capacity": 72,
      "time": "(一)5-7",
      "englishTaught": "否",
      "distanceLearning": "否",
      "syllabus": null,
      "note": ""
    },
    {
      "selectCode": "1633",
      "campus": "燕巢校區",
      "division": "日間部四技",
      "department": "人力資源發展系",
      "className": "四人三甲",
      "combinedClassName": "",
      "courseCode": "251C10208",
      "courseName": "作業管理",
      "credits": 3,
      "lectureHours": 3,
      "labHours": 0,
      "requiredOrElective": "選修",
      "instructor": "高世州",
      "classroom": "HS517",
      "enrolled": 43,
      "capacity": 70,
      "time": "(四)5-7",
      "englishTaught": "否",
      "distanceLearning": "否",
      "syllabus": null,
      "note": ""
    },
    {
      "selectCode": "1634",
      "campus": "燕巢校區",
      "division": "日間部四技",
      "department": "人力資源發展系",
      "className": "四人三甲",
      "combinedClassName": "",
      "courseCode": "251C00095",
      "courseName": "勞動法(一)",
      "credits": 3,
      "lectureHours": 3,
      "labHours": 0,
      "requiredOrElective": "必修",
      "instructor": "鄭克強",
      "classroom": "HS517",
      "enrolled": 59,
      "capacity": 70,
      "time": "(三)2-4",
      "englishTaught": "否",
      "distanceLearning": "否",
      "syllabus": null,
      "note": ""
    },
    {
      "selectCode": "1635",
      "campus": "燕巢校區",
      "division": "日間部四技",
      "department": "人力資源發展系",
      "className": "四人三甲",
      "combinedClassName": "",
      "courseCode": "251C00107",
      "courseName": "績效管理",
      "credits": 3,
      "lectureHours": 3,
      "labHours": 0,
      "requiredOrElective": "必修",
      "instructor": "黃佳純",
      "classroom": "HS517",
      "enrolled": 56,
      "capacity": 70,
      "time": "(二)5-7",
      "englishTaught": "否",
      "distanceLearning": "否",
      "syllabus": null,
      "note": ""
    },
    {
      "selectCode": "1636",
      "campus": "燕巢校區",
      "division": "日間部四技",
      "department": "人力資源發展系",
      "className": "四人三甲",
      "combinedClassName": "",
      "courseCode": "251C00108",
      "courseName": "薪資管理",
      "credits": 3,
      "lectureHours": 3,
      "labHours": 0,
      "requiredOrElective": "必修",
      "instructor": "陳必碩",
      "classroom": "HS517",
      "enrolled": 57,
      "capacity": 70,
      "time": "(一)5-7",
      "englishTaught": "否",
      "distanceLearning": "否",
      "syllabus": null,
      "note": ""
    },
    {
      "selectCode": "1637",
      "campus": "燕巢校區",
      "division": "日間部四技",
      "department": "人力資源發展系",
      "className": "四人三甲",
      "combinedClassName": "",
      "courseCode": "251C10213",
      "courseName": "統計應用分析軟體",
      "credits": 3,
      "lectureHours": 3,
      "labHours": 0,
      "requiredOrElective": "選修",
      "instructor": "翁慈君",
      "classroom": "HS519",
      "enrolled": 41,
      "capacity": 70,
      "time": "(一)2-4",
      "englishTaught": "否",
      "distanceLearning": "否",
      "syllabus": null,
      "note": ""
    },
    {
      "selectCode": "1638",
      "campus": "燕巢校區",
      "division": "日間部四技",
      "department": "人力資源發展系",
      "className": "四人三甲",
      "combinedClassName": "",
      "courseCode": "251C10289",
      "courseName": "職場發展與企業導航",
      "credits": 3,
      "lectureHours": 3,
      "labHours": 0,
      "requiredOrElective": "選修",
      "instructor": "陳必碩",
      "classroom": "HS517",
      "enrolled": 48,
      "capacity": 70,
      "time": "(二)2-4",
      "englishTaught": "否",
      "distanceLearning": "否",
      "syllabus": null,
      "note": ""
    },
    {
      "selectCode": "1639",
      "campus": "燕巢校區",
      "division": "日間部四技",
      "department": "人力資源發展系",
      "className": "四人四甲",
      "combinedClassName": "",
      "courseCode": "251C10272",
      "courseName": "國際企業管理",
      "credits": 3,
      "lectureHours": 3,
      "labHours": 0,
      "requiredOrElective": "選修",
      "instructor": "黃佩文",
      "classroom": "HS516",
      "enrolled": 38,
      "capacity": 66,
      "time": "(二)2-4",
      "englishTaught": "否",
      "distanceLearning": "否",
      "syllabus": null,
      "note": ""
    },
    {
      "selectCode": "1640",
      "campus": "燕巢校區",
      "division": "日間部四技",
      "department": "人力資源發展系",
      "className": "四人四甲",
      "combinedClassName": "",
      "courseCode": "251C00286",
      "courseName": "實務專題(二)",
      "credits": 1,
      "lectureHours": 3,
      "labHours": 0,
      "requiredOrElective": "必修",
      "instructor": "吳淑敏,王湧泉,翁慈君,董玉娟,許淑寬,鄭克強,陳儀蓉,陳必碩,黃佳純,黃瓊慧",
      "classroom": "HS516",
      "enrolled": 59,
      "capacity": 66,
      "time": "(四)1",
      "englishTaught": "否",
      "distanceLearning": "否",
      "syllabus": null,
      "note": ""
    },
    {
      "selectCode": "1641",
      "campus": "燕巢校區",
      "division": "日間部四技",
      "department": "人力資源發展系",
      "className": "四人四甲",
      "combinedClassName": "",
      "courseCode": "251C00110",
      "courseName": "人力資源資訊管理系統",
      "credits": 3,
      "lectureHours": 3,
      "labHours": 0,
      "requiredOrElective": "必修",
      "instructor": "翁慈君,王湧泉",
      "classroom": "HS519",
      "enrolled": 59,
      "capacity": 70,
      "time": "(三)2-4",
      "englishTaught": "否",
      "distanceLearning": "否",
      "syllabus": null,
      "note": ""
    },
    {
      "selectCode": "1642",
      "campus": "燕巢校區",
      "division": "日間部四技",
      "department": "人力資源發展系",
      "className": "四人四甲",
      "combinedClassName": "",
      "courseCode": "251C10291",
      "courseName": "進階職場英文(一)",
      "credits": 3,
      "lectureHours": 3,
      "labHours": 0,
      "requiredOrElective": "選修",
      "instructor": "吳淑敏",
      "classroom": "HS509",
      "enrolled": 27,
      "capacity": 40,
      "time": "(三)7-9",
      "englishTaught": "是",
      "distanceLearning": "否",
      "syllabus": null,
      "note": "【經111-2校課通過補助】英語授課"
    }
  ]
}
