{
  "scrapedAt": "2025-12-28T16:59:45.761Z",
  "sourceUrl": "https://webap.nkust.edu.tw/nkust/ag_pro/ag202.jsp",
  "request": {
    "yms_yms": "113#2",
    "cmp_area_id": "3",
    "dgr_id": "14",
    "unt_id": "UJ16",
    "clyear": "%",
    "week": "%",
    "period": "%",
    "reading": "reading"
  },
  "unit": {
    "id": "UJ16",
    "label": "(外語學院)外院學程[第一]"
  },
  "warning": null,
  "header": [
    "選課代號",
    "上課校區",
    "部別",
    "科系",
    "班級",
    "合班班級",
    "永久課號",
    "科目名稱",
    "學分",
    "授課時數",
    "實習時數",
    "必/選",
    "授課教師",
    "教室",
    "修課人數",
    "人數上限",
    "上課時間",
    "全英語授課",
    "遠距教學",
    "授課大綱",
    "備註"
  ],
  "courses": [
    {
      "selectCode": "5539",
      "campus": "第一校區",
      "division": "日間部四技",
      "department": "外院學程[第一]",
      "className": "外院學程一甲",
      "combinedClassName": "",
      "courseCode": "167C10089",
      "courseName": "人工智慧導論",
      "credits": 3,
      "lectureHours": 3,
      "labHours": 0,
      "requiredOrElective": "選修",
      "instructor": "阮家慶",
      "classroom": "D416",
      "enrolled": 26,
      "capacity": 36,
      "time": "(一)2-4",
      "englishTaught": "否",
      "distanceLearning": "否",
      "syllabus": null,
      "note": ""
    },
    {
      "selectCode": "1841",
      "campus": "第一校區",
      "division": "日間部四技",
      "department": "外院學程[第一]",
      "className": "外院學程三甲",
      "combinedClassName": "外院學程三乙",
      "courseCode": "167C10051",
      "courseName": "物流管理",
      "credits": 3,
      "lectureHours": 3,
      "labHours": 0,
      "requiredOrElective": "選修",
      "instructor": "蘇湘婷",
      "classroom": "E002",
      "enrolled": 65,
      "capacity": 55,
      "time": "(四)5-7",
      "englishTaught": "否",
      "distanceLearning": "否",
      "syllabus": null,
      "note": ""
    },
    {
      "selectCode": "1842",
      "campus": "第一校區",
      "division": "日間部四技",
      "department": "外院學程[第一]",
      "className": "外院學程三甲",
      "combinedClassName": "",
      "courseCode": "167C10063",
      "courseName": "管理學",
      "credits": 3,
      "lectureHours": 3,
      "labHours": 0,
      "requiredOrElective": "選修",
      "instructor": "龍仕璋",
      "classroom": "E008",
      "enrolled": 90,
      "capacity": 90,
      "time": "(三)7-9",
      "englishTaught": "否",
      "distanceLearning": "否",
      "syllabus": null,
      "note": ""
    },
    {
      "selectCode": "1843",
      "campus": "第一校區",
      "division": "日間部四技",
      "department": "外院學程[第一]",
      "className": "外院學程三甲",
      "combinedClassName": "外院學程三乙",
      "courseCode": "167C10047",
      "courseName": "網路行銷",
      "credits": 3,
      "lectureHours": 3,
      "labHours": 0,
      "requiredOrElective": "選修",
      "instructor": "黃永欽",
      "classroom": "E003",
      "enrolled": 41,
      "capacity": 35,
      "time": "(三)7-9",
      "englishTaught": "否",
      "distanceLearning": "否",
      "syllabus": null,
      "note": ""
    },
    {
      "selectCode": "1844",
      "campus": "第一校區",
      "division": "日間部四技",
      "department": "外院學程[第一]",
      "className": "外院學程三甲",
      "combinedClassName": "外院學程三乙",
      "courseCode": "167C10079",
      "courseName": "程式設計(二)",
      "credits": 3,
      "lectureHours": 3,
      "labHours": 0,
      "requiredOrElective": "選修",
      "instructor": "黃煒盛,徐偉智",
      "classroom": "D418",
      "enrolled": 19,
      "capacity": 38,
      "time": "(四)5-7",
      "englishTaught": "否",
      "distanceLearning": "否",
      "syllabus": null,
      "note": ""
    },
    {
      "selectCode": "1845",
      "campus": "第一校區",
      "division": "日間部四技",
      "department": "外院學程[第一]",
      "className": "外院學程三甲",
      "combinedClassName": "外院學程三乙",
      "courseCode": "167C10073",
      "courseName": "服務品質管理",
      "credits": 3,
      "lectureHours": 3,
      "labHours": 0,
      "requiredOrElective": "選修",
      "instructor": "袁徵霖",
      "classroom": "D101",
      "enrolled": 20,
      "capacity": 35,
      "time": "(四)5-7",
      "englishTaught": "否",
      "distanceLearning": "否",
      "syllabus": null,
      "note": ""
    },
    {
      "selectCode": "1846",
      "campus": "第一校區",
      "division": "日間部四技",
      "department": "外院學程[第一]",
      "className": "外院學程三甲",
      "combinedClassName": "外院學程三乙",
      "courseCode": "167C10072",
      "courseName": "商品展覽與介紹",
      "credits": 3,
      "lectureHours": 3,
      "labHours": 0,
      "requiredOrElective": "選修",
      "instructor": "黃海深",
      "classroom": "D416",
      "enrolled": 10,
      "capacity": 35,
      "time": "(二)5-7",
      "englishTaught": "否",
      "distanceLearning": "否",
      "syllabus": null,
      "note": ""
    },
    {
      "selectCode": "1849",
      "campus": "第一校區",
      "division": "日間部四技",
      "department": "外院學程[第一]",
      "className": "外院學程三甲",
      "combinedClassName": "外院學程三乙",
      "courseCode": "167C10082",
      "courseName": "動畫影片製作",
      "credits": 3,
      "lectureHours": 3,
      "labHours": 0,
      "requiredOrElective": "選修",
      "instructor": "許淑娟",
      "classroom": "D419電腦教室",
      "enrolled": 20,
      "capacity": 20,
      "time": "(四)5-7",
      "englishTaught": "否",
      "distanceLearning": "否",
      "syllabus": null,
      "note": ""
    },
    {
      "selectCode": "1850",
      "campus": "第一校區",
      "division": "日間部四技",
      "department": "外院學程[第一]",
      "className": "外院學程三甲",
      "combinedClassName": "外院學程三乙",
      "courseCode": "167C10083",
      "courseName": "科技應用與文創",
      "credits": 3,
      "lectureHours": 3,
      "labHours": 0,
      "requiredOrElective": "選修",
      "instructor": "李國維",
      "classroom": "J009",
      "enrolled": 40,
      "capacity": 40,
      "time": "(四)5-7",
      "englishTaught": "否",
      "distanceLearning": "否",
      "syllabus": null,
      "note": ""
    },
    {
      "selectCode": "1851",
      "campus": "第一校區",
      "division": "日間部四技",
      "department": "外院學程[第一]",
      "className": "外院學程三甲",
      "combinedClassName": "外院學程三乙",
      "courseCode": "167C10084",
      "courseName": "商務網站設計",
      "credits": 3,
      "lectureHours": 3,
      "labHours": 0,
      "requiredOrElective": "選修",
      "instructor": "黃海深",
      "classroom": "D419電腦教室",
      "enrolled": 17,
      "capacity": 20,
      "time": "(三)7-9",
      "englishTaught": "否",
      "distanceLearning": "否",
      "syllabus": null,
      "note": ""
    },
    {
      "selectCode": "1853",
      "campus": "第一校區",
      "division": "日間部四技",
      "department": "外院學程[第一]",
      "className": "外院學程三甲",
      "combinedClassName": "外院學程三乙",
      "courseCode": "167C10048",
      "courseName": "商務契約",
      "credits": 3,
      "lectureHours": 3,
      "labHours": 0,
      "requiredOrElective": "選修",
      "instructor": "蔡宗廷",
      "classroom": "E305",
      "enrolled": 19,
      "capacity": 55,
      "time": "(四)5-7",
      "englishTaught": "否",
      "distanceLearning": "否",
      "syllabus": null,
      "note": ""
    },
    {
      "selectCode": "1854",
      "campus": "第一校區",
      "division": "日間部四技",
      "department": "外院學程[第一]",
      "className": "外院學程三甲",
      "combinedClassName": "外院學程三乙",
      "courseCode": "167C10071",
      "courseName": "旅遊實務",
      "credits": 3,
      "lectureHours": 3,
      "labHours": 0,
      "requiredOrElective": "選修",
      "instructor": "廖慧蓉",
      "classroom": "D517",
      "enrolled": 21,
      "capacity": 24,
      "time": "(四)5-7",
      "englishTaught": "否",
      "distanceLearning": "否",
      "syllabus": null,
      "note": ""
    },
    {
      "selectCode": "1855",
      "campus": "第一校區",
      "division": "日間部四技",
      "department": "外院學程[第一]",
      "className": "外院學程三甲",
      "combinedClassName": "外院學程三乙",
      "courseCode": "167C10050",
      "courseName": "個人投資理財",
      "credits": 3,
      "lectureHours": 3,
      "labHours": 0,
      "requiredOrElective": "選修",
      "instructor": "蔡繡容",
      "classroom": "C434",
      "enrolled": 33,
      "capacity": 30,
      "time": "(四)5-7",
      "englishTaught": "否",
      "distanceLearning": "否",
      "syllabus": null,
      "note": ""
    },
    {
      "selectCode": "1856",
      "campus": "第一校區",
      "division": "日間部四技",
      "department": "外院學程[第一]",
      "className": "外院學程三甲",
      "combinedClassName": "外院學程三乙",
      "courseCode": "167C10075",
      "courseName": "東協文化概覽",
      "credits": 3,
      "lectureHours": 3,
      "labHours": 0,
      "requiredOrElective": "選修",
      "instructor": "倪華緣",
      "classroom": "D416",
      "enrolled": 35,
      "capacity": 36,
      "time": "(三)7-9",
      "englishTaught": "否",
      "distanceLearning": "否",
      "syllabus": null,
      "note": ""
    },
    {
      "selectCode": "1857",
      "campus": "第一校區",
      "division": "日間部四技",
      "department": "外院學程[第一]",
      "className": "外院學程三甲",
      "combinedClassName": "外院學程三乙",
      "courseCode": "167C10056",
      "courseName": "風險管理導論",
      "credits": 3,
      "lectureHours": 3,
      "labHours": 0,
      "requiredOrElective": "選修",
      "instructor": "蘇湘婷",
      "classroom": "E305",
      "enrolled": 52,
      "capacity": 35,
      "time": "(五)2-4",
      "englishTaught": "否",
      "distanceLearning": "否",
      "syllabus": null,
      "note": ""
    },
    {
      "selectCode": "1858",
      "campus": "第一校區",
      "division": "日間部四技",
      "department": "外院學程[第一]",
      "className": "外院學程三甲",
      "combinedClassName": "外院學程三乙",
      "courseCode": "167C10062",
      "courseName": "電子商務與法律",
      "credits": 3,
      "lectureHours": 3,
      "labHours": 0,
      "requiredOrElective": "選修",
      "instructor": "鄭莞鈴",
      "classroom": "E003",
      "enrolled": 38,
      "capacity": 90,
      "time": "(四)5-7",
      "englishTaught": "否",
      "distanceLearning": "否",
      "syllabus": null,
      "note": ""
    },
    {
      "selectCode": "1859",
      "campus": "第一校區",
      "division": "日間部四技",
      "department": "外院學程[第一]",
      "className": "外院學程三甲",
      "combinedClassName": "外院學程三乙",
      "courseCode": "167C10046",
      "courseName": "大數據商業應用分析",
      "credits": 3,
      "lectureHours": 3,
      "labHours": 0,
      "requiredOrElective": "選修",
      "instructor": "阮至永",
      "classroom": "D418",
      "enrolled": 29,
      "capacity": 38,
      "time": "(三)7-9",
      "englishTaught": "否",
      "distanceLearning": "否",
      "syllabus": null,
      "note": ""
    },
    {
      "selectCode": "1860",
      "campus": "第一校區",
      "division": "日間部四技",
      "department": "外院學程[第一]",
      "className": "外院學程三甲",
      "combinedClassName": "外院學程三乙",
      "courseCode": "167C10055",
      "courseName": "基礎會計與財務報表分析",
      "credits": 3,
      "lectureHours": 3,
      "labHours": 0,
      "requiredOrElective": "選修",
      "instructor": "趙雅儀",
      "classroom": "E003",
      "enrolled": 45,
      "capacity": 90,
      "time": "(五)2-4",
      "englishTaught": "否",
      "distanceLearning": "否",
      "syllabus": null,
      "note": ""
    },
    {
      "selectCode": "5540",
      "campus": "第一校區",
      "division": "日間部四技",
      "department": "外院學程[第一]",
      "className": "外院學程三甲",
      "combinedClassName": "外院學程三乙",
      "courseCode": "167C10086",
      "courseName": "AI數位人文導論",
      "credits": 3,
      "lectureHours": 3,
      "labHours": 0,
      "requiredOrElective": "選修",
      "instructor": "吳怡萍,阮家慶",
      "classroom": "D416",
      "enrolled": 13,
      "capacity": 36,
      "time": "(一)5-7",
      "englishTaught": "否",
      "distanceLearning": "否",
      "syllabus": null,
      "note": ""
    },
    {
      "selectCode": "1841",
      "campus": "第一校區",
      "division": "日間部四技",
      "department": "外院學程[第一]",
      "className": "外院學程三乙",
      "combinedClassName": "",
      "courseCode": "167C10051",
      "courseName": "物流管理",
      "credits": 3,
      "lectureHours": 3,
      "labHours": 0,
      "requiredOrElective": "選修",
      "instructor": "蘇湘婷",
      "classroom": "E002",
      "enrolled": 65,
      "capacity": 55,
      "time": "(四)5-7",
      "englishTaught": "否",
      "distanceLearning": "否",
      "syllabus": null,
      "note": ""
    },
    {
      "selectCode": "1843",
      "campus": "第一校區",
      "division": "日間部四技",
      "department": "外院學程[第一]",
      "className": "外院學程三乙",
      "combinedClassName": "",
      "courseCode": "167C10047",
      "courseName": "網路行銷",
      "credits": 3,
      "lectureHours": 3,
      "labHours": 0,
      "requiredOrElective": "選修",
      "instructor": "黃永欽",
      "classroom": "E003",
      "enrolled": 41,
      "capacity": 35,
      "time": "(三)7-9",
      "englishTaught": "否",
      "distanceLearning": "否",
      "syllabus": null,
      "note": ""
    },
    {
      "selectCode": "1844",
      "campus": "第一校區",
      "division": "日間部四技",
      "department": "外院學程[第一]",
      "className": "外院學程三乙",
      "combinedClassName": "",
      "courseCode": "167C10079",
      "courseName": "程式設計(二)",
      "credits": 3,
      "lectureHours": 3,
      "labHours": 0,
      "requiredOrElective": "選修",
      "instructor": "黃煒盛,徐偉智",
      "classroom": "D418",
      "enrolled": 19,
      "capacity": 38,
      "time": "(四)5-7",
      "englishTaught": "否",
      "distanceLearning": "否",
      "syllabus": null,
      "note": ""
    },
    {
      "selectCode": "1845",
      "campus": "第一校區",
      "division": "日間部四技",
      "department": "外院學程[第一]",
      "className": "外院學程三乙",
      "combinedClassName": "",
      "courseCode": "167C10073",
      "courseName": "服務品質管理",
      "credits": 3,
      "lectureHours": 3,
      "labHours": 0,
      "requiredOrElective": "選修",
      "instructor": "袁徵霖",
      "classroom": "D101",
      "enrolled": 20,
      "capacity": 35,
      "time": "(四)5-7",
      "englishTaught": "否",
      "distanceLearning": "否",
      "syllabus": null,
      "note": ""
    },
    {
      "selectCode": "1846",
      "campus": "第一校區",
      "division": "日間部四技",
      "department": "外院學程[第一]",
      "className": "外院學程三乙",
      "combinedClassName": "",
      "courseCode": "167C10072",
      "courseName": "商品展覽與介紹",
      "credits": 3,
      "lectureHours": 3,
      "labHours": 0,
      "requiredOrElective": "選修",
      "instructor": "黃海深",
      "classroom": "D416",
      "enrolled": 10,
      "capacity": 35,
      "time": "(二)5-7",
      "englishTaught": "否",
      "distanceLearning": "否",
      "syllabus": null,
      "note": ""
    },
    {
      "selectCode": "1849",
      "campus": "第一校區",
      "division": "日間部四技",
      "department": "外院學程[第一]",
      "className": "外院學程三乙",
      "combinedClassName": "",
      "courseCode": "167C10082",
      "courseName": "動畫影片製作",
      "credits": 3,
      "lectureHours": 3,
      "labHours": 0,
      "requiredOrElective": "選修",
      "instructor": "許淑娟",
      "classroom": "D419電腦教室",
      "enrolled": 20,
      "capacity": 20,
      "time": "(四)5-7",
      "englishTaught": "否",
      "distanceLearning": "否",
      "syllabus": null,
      "note": ""
    },
    {
      "selectCode": "1850",
      "campus": "第一校區",
      "division": "日間部四技",
      "department": "外院學程[第一]",
      "className": "外院學程三乙",
      "combinedClassName": "",
      "courseCode": "167C10083",
      "courseName": "科技應用與文創",
      "credits": 3,
      "lectureHours": 3,
      "labHours": 0,
      "requiredOrElective": "選修",
      "instructor": "李國維",
      "classroom": "J009",
      "enrolled": 40,
      "capacity": 40,
      "time": "(四)5-7",
      "englishTaught": "否",
      "distanceLearning": "否",
      "syllabus": null,
      "note": ""
    },
    {
      "selectCode": "1851",
      "campus": "第一校區",
      "division": "日間部四技",
      "department": "外院學程[第一]",
      "className": "外院學程三乙",
      "combinedClassName": "",
      "courseCode": "167C10084",
      "courseName": "商務網站設計",
      "credits": 3,
      "lectureHours": 3,
      "labHours": 0,
      "requiredOrElective": "選修",
      "instructor": "黃海深",
      "classroom": "D419電腦教室",
      "enrolled": 17,
      "capacity": 20,
      "time": "(三)7-9",
      "englishTaught": "否",
      "distanceLearning": "否",
      "syllabus": null,
      "note": ""
    },
    {
      "selectCode": "1853",
      "campus": "第一校區",
      "division": "日間部四技",
      "department": "外院學程[第一]",
      "className": "外院學程三乙",
      "combinedClassName": "",
      "courseCode": "167C10048",
      "courseName": "商務契約",
      "credits": 3,
      "lectureHours": 3,
      "labHours": 0,
      "requiredOrElective": "選修",
      "instructor": "蔡宗廷",
      "classroom": "E305",
      "enrolled": 19,
      "capacity": 55,
      "time": "(四)5-7",
      "englishTaught": "否",
      "distanceLearning": "否",
      "syllabus": null,
      "note": ""
    },
    {
      "selectCode": "1854",
      "campus": "第一校區",
      "division": "日間部四技",
      "department": "外院學程[第一]",
      "className": "外院學程三乙",
      "combinedClassName": "",
      "courseCode": "167C10071",
      "courseName": "旅遊實務",
      "credits": 3,
      "lectureHours": 3,
      "labHours": 0,
      "requiredOrElective": "選修",
      "instructor": "廖慧蓉",
      "classroom": "D517",
      "enrolled": 21,
      "capacity": 24,
      "time": "(四)5-7",
      "englishTaught": "否",
      "distanceLearning": "否",
      "syllabus": null,
      "note": ""
    },
    {
      "selectCode": "1855",
      "campus": "第一校區",
      "division": "日間部四技",
      "department": "外院學程[第一]",
      "className": "外院學程三乙",
      "combinedClassName": "",
      "courseCode": "167C10050",
      "courseName": "個人投資理財",
      "credits": 3,
      "lectureHours": 3,
      "labHours": 0,
      "requiredOrElective": "選修",
      "instructor": "蔡繡容",
      "classroom": "C434",
      "enrolled": 33,
      "capacity": 30,
      "time": "(四)5-7",
      "englishTaught": "否",
      "distanceLearning": "否",
      "syllabus": null,
      "note": ""
    },
    {
      "selectCode": "1856",
      "campus": "第一校區",
      "division": "日間部四技",
      "department": "外院學程[第一]",
      "className": "外院學程三乙",
      "combinedClassName": "",
      "courseCode": "167C10075",
      "courseName": "東協文化概覽",
      "credits": 3,
      "lectureHours": 3,
      "labHours": 0,
      "requiredOrElective": "選修",
      "instructor": "倪華緣",
      "classroom": "D416",
      "enrolled": 35,
      "capacity": 36,
      "time": "(三)7-9",
      "englishTaught": "否",
      "distanceLearning": "否",
      "syllabus": null,
      "note": ""
    },
    {
      "selectCode": "1857",
      "campus": "第一校區",
      "division": "日間部四技",
      "department": "外院學程[第一]",
      "className": "外院學程三乙",
      "combinedClassName": "",
      "courseCode": "167C10056",
      "courseName": "風險管理導論",
      "credits": 3,
      "lectureHours": 3,
      "labHours": 0,
      "requiredOrElective": "選修",
      "instructor": "蘇湘婷",
      "classroom": "E305",
      "enrolled": 52,
      "capacity": 35,
      "time": "(五)2-4",
      "englishTaught": "否",
      "distanceLearning": "否",
      "syllabus": null,
      "note": ""
    },
    {
      "selectCode": "1858",
      "campus": "第一校區",
      "division": "日間部四技",
      "department": "外院學程[第一]",
      "className": "外院學程三乙",
      "combinedClassName": "",
      "courseCode": "167C10062",
      "courseName": "電子商務與法律",
      "credits": 3,
      "lectureHours": 3,
      "labHours": 0,
      "requiredOrElective": "選修",
      "instructor": "鄭莞鈴",
      "classroom": "E003",
      "enrolled": 38,
      "capacity": 90,
      "time": "(四)5-7",
      "englishTaught": "否",
      "distanceLearning": "否",
      "syllabus": null,
      "note": ""
    },
    {
      "selectCode": "1859",
      "campus": "第一校區",
      "division": "日間部四技",
      "department": "外院學程[第一]",
      "className": "外院學程三乙",
      "combinedClassName": "",
      "courseCode": "167C10046",
      "courseName": "大數據商業應用分析",
      "credits": 3,
      "lectureHours": 3,
      "labHours": 0,
      "requiredOrElective": "選修",
      "instructor": "阮至永",
      "classroom": "D418",
      "enrolled": 29,
      "capacity": 38,
      "time": "(三)7-9",
      "englishTaught": "否",
      "distanceLearning": "否",
      "syllabus": null,
      "note": ""
    },
    {
      "selectCode": "1860",
      "campus": "第一校區",
      "division": "日間部四技",
      "department": "外院學程[第一]",
      "className": "外院學程三乙",
      "combinedClassName": "",
      "courseCode": "167C10055",
      "courseName": "基礎會計與財務報表分析",
      "credits": 3,
      "lectureHours": 3,
      "labHours": 0,
      "requiredOrElective": "選修",
      "instructor": "趙雅儀",
      "classroom": "E003",
      "enrolled": 45,
      "capacity": 90,
      "time": "(五)2-4",
      "englishTaught": "否",
      "distanceLearning": "否",
      "syllabus": null,
      "note": ""
    },
    {
      "selectCode": "1861",
      "campus": "第一校區",
      "division": "日間部四技",
      "department": "外院學程[第一]",
      "className": "外院學程三乙",
      "combinedClassName": "",
      "courseCode": "167C10063",
      "courseName": "管理學",
      "credits": 3,
      "lectureHours": 3,
      "labHours": 0,
      "requiredOrElective": "選修",
      "instructor": "趙雅儀",
      "classroom": "E003",
      "enrolled": 44,
      "capacity": 55,
      "time": "(一)7-9",
      "englishTaught": "否",
      "distanceLearning": "否",
      "syllabus": null,
      "note": ""
    },
    {
      "selectCode": "5540",
      "campus": "第一校區",
      "division": "日間部四技",
      "department": "外院學程[第一]",
      "className": "外院學程三乙",
      "combinedClassName": "",
      "courseCode": "167C10086",
      "courseName": "AI數位人文導論",
      "credits": 3,
      "lectureHours": 3,
      "labHours": 0,
      "requiredOrElective": "選修",
      "instructor": "吳怡萍,阮家慶",
      "classroom": "D416",
      "enrolled": 13,
      "capacity": 36,
      "time": "(一)5-7",
      "englishTaught": "否",
      "distanceLearning": "否",
      "syllabus": null,
      "note": ""
    }
  ]
}
